pipsi_tool/__init__.py
pipsi_tool/__main__.py
pipsi_tool/pipsi_package.py
pipsi_tool/utils.py
pipsi_tool/commands/__init__.py
pipsi_tool/commands/command.py
pipsi_tool/commands/reinstall_all.py
pipsi_tool/commands/upgrade_all.py
pipsi_tool-1.0.3.dist-info/DESCRIPTION.rst
pipsi_tool-1.0.3.dist-info/METADATA
pipsi_tool-1.0.3.dist-info/RECORD
pipsi_tool-1.0.3.dist-info/WHEEL
pipsi_tool-1.0.3.dist-info/entry_points.txt
pipsi_tool-1.0.3.dist-info/metadata.json
pipsi_tool-1.0.3.dist-info/top_level.txt
