Metadata-Version: 2.0
Name: pipsi-tool
Version: 1.0.3
Summary: pipsi-tool is set of helpers for https://github.com/mitsuhiko/pipsi
Home-page: http://msztolcman.github.io/pipsi-tool/
Author: Marcin Sztolcman
Author-email: marcin@urzenia.net
License: MIT
Keywords: pipsi
Platform: UNKNOWN
Classifier: Development Status :: 4 - Beta
Classifier: Environment :: Console
Classifier: Intended Audience :: Developers
Classifier: License :: OSI Approved :: MIT License
Classifier: Topic :: Utilities
Classifier: Programming Language :: Python :: 3.5
Requires-Dist: argparse
